[{"Team":"Adelaide Crows","Last":1847,"LastOpp":1452,"Season":1739,"SeasonOpp":1562,"Last3":1693,"Last3Opp":1606,"Top3Mid":110,"Top3OppMid":106,"TopRuc":84,"TopOppRuc":76,"Top2Def":101,"Top2OppDef":103,"Top2For":102,"Top2OppFor":82},{"Team":"Brisbane Lions","Last":1782,"LastOpp":1517,"Season":1752,"SeasonOpp":1548,"Last3":1726,"Last3Opp":1575,"Top3Mid":123,"Top3OppMid":102,"TopRuc":83,"TopOppRuc":81,"Top2Def":110,"Top2OppDef":97,"Top2For":77,"Top2OppFor":80},{"Team":"Carlton","Last":1452,"LastOpp":1847,"Season":1682,"SeasonOpp":1618,"Last3":1726,"Last3Opp":1573,"Top3Mid":114,"Top3OppMid":108,"TopRuc":115,"TopOppRuc":87,"Top2Def":94,"Top2OppDef":91,"Top2For":88,"Top2OppFor":84},{"Team":"Collingwood","Last":1649,"LastOpp":1653,"Season":1713,"SeasonOpp":1587,"Last3":1723,"Last3Opp":1578,"Top3Mid":110,"Top3OppMid":106,"TopRuc":113,"TopOppRuc":93,"Top2Def":100,"Top2OppDef":100,"Top2For":80,"Top2OppFor":81},{"Team":"Essendon","Last":1716,"LastOpp":1583,"Season":1627,"SeasonOpp":1673,"Last3":1622,"Last3Opp":1677,"Top3Mid":111,"Top3OppMid":107,"TopRuc":90,"TopOppRuc":115,"Top2Def":93,"Top2OppDef":94,"Top2For":94,"Top2OppFor":87},{"Team":"Fremantle","Last":1449,"LastOpp":1849,"Season":1636,"SeasonOpp":1664,"Last3":1556,"Last3Opp":1743,"Top3Mid":107,"Top3OppMid":105,"TopRuc":97,"TopOppRuc":107,"Top2Def":102,"Top2OppDef":104,"Top2For":86,"Top2OppFor":87},{"Team":"GWS GIANTS","Last":1675,"LastOpp":1627,"Season":1740,"SeasonOpp":1561,"Last3":1685,"Last3Opp":1616,"Top3Mid":107,"Top3OppMid":97,"TopRuc":73,"TopOppRuc":96,"Top2Def":124,"Top2OppDef":96,"Top2For":93,"Top2OppFor":78},{"Team":"Geelong Cats","Last":1653,"LastOpp":1649,"Season":1646,"SeasonOpp":1655,"Last3":1552,"Last3Opp":1750,"Top3Mid":106,"Top3OppMid":110,"TopRuc":80,"TopOppRuc":106,"Top2Def":93,"Top2OppDef":106,"Top2For":93,"Top2OppFor":80},{"Team":"Gold Coast SUNS","Last":1517,"LastOpp":1782,"Season":1694,"SeasonOpp":1606,"Last3":1610,"Last3Opp":1690,"Top3Mid":113,"Top3OppMid":105,"TopRuc":103,"TopOppRuc":80,"Top2Def":108,"Top2OppDef":107,"Top2For":88,"Top2OppFor":79},{"Team":"Hawthorn","Last":1974,"LastOpp":1325,"Season":1766,"SeasonOpp":1533,"Last3":1895,"Last3Opp":1407,"Top3Mid":110,"Top3OppMid":102,"TopRuc":108,"TopOppRuc":92,"Top2Def":100,"Top2OppDef":90,"Top2For":93,"Top2OppFor":79},{"Team":"Melbourne","Last":1794,"LastOpp":1506,"Season":1643,"SeasonOpp":1656,"Last3":1830,"Last3Opp":1468,"Top3Mid":102,"Top3OppMid":105,"TopRuc":130,"TopOppRuc":97,"Top2Def":105,"Top2OppDef":103,"Top2For":76,"Top2OppFor":92},{"Team":"North Melbourne","Last":1583,"LastOpp":1716,"Season":1612,"SeasonOpp":1688,"Last3":1547,"Last3Opp":1754,"Top3Mid":103,"Top3OppMid":115,"TopRuc":122,"TopOppRuc":75,"Top2Def":93,"Top2OppDef":104,"Top2For":95,"Top2OppFor":101},{"Team":"Port Adelaide","Last":1400,"LastOpp":1897,"Season":1644,"SeasonOpp":1657,"Last3":1549,"Last3Opp":1751,"Top3Mid":114,"Top3OppMid":103,"TopRuc":82,"TopOppRuc":106,"Top2Def":96,"Top2OppDef":99,"Top2For":86,"Top2OppFor":96},{"Team":"Richmond","Last":1325,"LastOpp":1974,"Season":1477,"SeasonOpp":1822,"Last3":1474,"Last3Opp":1824,"Top3Mid":95,"Top3OppMid":117,"TopRuc":99,"TopOppRuc":114,"Top2Def":93,"Top2OppDef":110,"Top2For":72,"Top2OppFor":96},{"Team":"St Kilda","Last":1849,"LastOpp":1449,"Season":1627,"SeasonOpp":1675,"Last3":1608,"Last3Opp":1691,"Top3Mid":105,"Top3OppMid":106,"TopRuc":90,"TopOppRuc":90,"Top2Def":109,"Top2OppDef":102,"Top2For":93,"Top2OppFor":82},{"Team":"Sydney Swans","Last":1627,"LastOpp":1675,"Season":1625,"SeasonOpp":1675,"Last3":1638,"Last3Opp":1664,"Top3Mid":99,"Top3OppMid":115,"TopRuc":95,"TopOppRuc":101,"Top2Def":105,"Top2OppDef":102,"Top2For":79,"Top2OppFor":82},{"Team":"West Coast Eagles","Last":1506,"LastOpp":1794,"Season":1404,"SeasonOpp":1897,"Last3":1484,"Last3Opp":1817,"Top3Mid":86,"Top3OppMid":117,"TopRuc":72,"TopOppRuc":132,"Top2Def":92,"Top2OppDef":104,"Top2For":75,"Top2OppFor":112},{"Team":"Western Bulldogs","Last":1897,"LastOpp":1400,"Season":1678,"SeasonOpp":1623,"Last3":1783,"Last3Opp":1516,"Top3Mid":118,"Top3OppMid":104,"TopRuc":103,"TopOppRuc":91,"Top2Def":96,"Top2OppDef":102,"Top2For":95,"Top2OppFor":85}]
