[{"Team":"Adelaide Crows","Last":1868,"LastOpp":1459,"Season":1572,"SeasonOpp":1448,"Last3":1724,"Last3Opp":1419,"Top3Mid":106,"Top3OppMid":100,"TopRuc":91,"TopOppRuc":83,"Top2Def":84,"Top2OppDef":82,"Top2For":90,"Top2OppFor":73},{"Team":"Brisbane Lions","Last":1662,"LastOpp":1305,"Season":1516,"SeasonOpp":1509,"Last3":1558,"Last3Opp":1413,"Top3Mid":102,"Top3OppMid":101,"TopRuc":81,"TopOppRuc":80,"Top2Def":84,"Top2OppDef":93,"Top2For":84,"Top2OppFor":77},{"Team":"Carlton","Last":1839,"LastOpp":1507,"Season":1600,"SeasonOpp":1501,"Last3":1611,"Last3Opp":1487,"Top3Mid":103,"Top3OppMid":99,"TopRuc":71,"TopOppRuc":79,"Top2Def":96,"Top2OppDef":88,"Top2For":92,"Top2OppFor":85},{"Team":"Collingwood","Last":1675,"LastOpp":1431,"Season":1563,"SeasonOpp":1476,"Last3":1604,"Last3Opp":1511,"Top3Mid":105,"Top3OppMid":100,"TopRuc":82,"TopOppRuc":86,"Top2Def":97,"Top2OppDef":93,"Top2For":76,"Top2OppFor":78},{"Team":"Essendon","Last":1507,"LastOpp":1333,"Season":1589,"SeasonOpp":1528,"Last3":1533,"Last3Opp":1428,"Top3Mid":106,"Top3OppMid":100,"TopRuc":68,"TopOppRuc":74,"Top2Def":94,"Top2OppDef":100,"Top2For":78,"Top2OppFor":82},{"Team":"Fremantle","Last":1741,"LastOpp":1489,"Season":1578,"SeasonOpp":1504,"Last3":1579,"Last3Opp":1553,"Top3Mid":105,"Top3OppMid":105,"TopRuc":101,"TopOppRuc":79,"Top2Def":97,"Top2OppDef":85,"Top2For":81,"Top2OppFor":80},{"Team":"Geelong Cats","Last":1338,"LastOpp":1555,"Season":1466,"SeasonOpp":1515,"Last3":1377,"Last3Opp":1492,"Top3Mid":91,"Top3OppMid":100,"TopRuc":72,"TopOppRuc":82,"Top2Def":86,"Top2OppDef":90,"Top2For":85,"Top2OppFor":85},{"Team":"Gold Coast Suns","Last":1431,"LastOpp":1675,"Season":1485,"SeasonOpp":1534,"Last3":1462,"Last3Opp":1591,"Top3Mid":102,"Top3OppMid":103,"TopRuc":85,"TopOppRuc":78,"Top2Def":88,"Top2OppDef":91,"Top2For":76,"Top2OppFor":78},{"Team":"GWS Giants","Last":1442,"LastOpp":1634,"Season":1561,"SeasonOpp":1532,"Last3":1574,"Last3Opp":1499,"Top3Mid":105,"Top3OppMid":96,"TopRuc":82,"TopOppRuc":94,"Top2Def":94,"Top2OppDef":94,"Top2For":91,"Top2OppFor":84},{"Team":"Hawthorn","Last":1507,"LastOpp":1839,"Season":1564,"SeasonOpp":1609,"Last3":1546,"Last3Opp":1646,"Top3Mid":97,"Top3OppMid":106,"TopRuc":69,"TopOppRuc":74,"Top2Def":101,"Top2OppDef":90,"Top2For":84,"Top2OppFor":88},{"Team":"Melbourne","Last":1634,"LastOpp":1442,"Season":1544,"SeasonOpp":1474,"Last3":1561,"Last3Opp":1494,"Top3Mid":106,"Top3OppMid":103,"TopRuc":92,"TopOppRuc":77,"Top2Def":84,"Top2OppDef":95,"Top2For":77,"Top2OppFor":69},{"Team":"North Melbourne","Last":1459,"LastOpp":1868,"Season":1455,"SeasonOpp":1649,"Last3":1424,"Last3Opp":1692,"Top3Mid":89,"Top3OppMid":107,"TopRuc":78,"TopOppRuc":81,"Top2Def":96,"Top2OppDef":92,"Top2For":81,"Top2OppFor":93},{"Team":"Port Adelaide","Last":1333,"LastOpp":1507,"Season":1452,"SeasonOpp":1452,"Last3":1402,"Last3Opp":1462,"Top3Mid":100,"Top3OppMid":95,"TopRuc":65,"TopOppRuc":97,"Top2Def":86,"Top2OppDef":90,"Top2For":81,"Top2OppFor":74},{"Team":"Richmond","Last":1305,"LastOpp":1662,"Season":1505,"SeasonOpp":1567,"Last3":1493,"Last3Opp":1573,"Top3Mid":107,"Top3OppMid":105,"TopRuc":93,"TopOppRuc":92,"Top2Def":94,"Top2OppDef":95,"Top2For":77,"Top2OppFor":83},{"Team":"St Kilda","Last":1596,"LastOpp":1745,"Season":1637,"SeasonOpp":1626,"Last3":1564,"Last3Opp":1624,"Top3Mid":99,"Top3OppMid":104,"TopRuc":111,"TopOppRuc":82,"Top2Def":97,"Top2OppDef":105,"Top2For":85,"Top2OppFor":89},{"Team":"Sydney Swans","Last":1555,"LastOpp":1338,"Season":1541,"SeasonOpp":1494,"Last3":1604,"Last3Opp":1331,"Top3Mid":103,"Top3OppMid":99,"TopRuc":79,"TopOppRuc":91,"Top2Def":91,"Top2OppDef":85,"Top2For":85,"Top2OppFor":81},{"Team":"West Coast Eagles","Last":1745,"LastOpp":1596,"Season":1437,"SeasonOpp":1670,"Last3":1393,"Last3Opp":1746,"Top3Mid":96,"Top3OppMid":109,"TopRuc":81,"TopOppRuc":97,"Top2Def":94,"Top2OppDef":92,"Top2For":78,"Top2OppFor":102},{"Team":"Western Bulldogs","Last":1489,"LastOpp":1741,"Season":1567,"SeasonOpp":1543,"Last3":1557,"Last3Opp":1508,"Top3Mid":110,"Top3OppMid":100,"TopRuc":118,"TopOppRuc":95,"Top2Def":92,"Top2OppDef":95,"Top2For":78,"Top2OppFor":77}]
