[{"Team":"Adelaide Crows","Last":1709,"LastOpp":1589,"Season":1709,"SeasonOpp":1591,"Last3":1704,"Last3Opp":1595,"Top3Mid":113,"Top3OppMid":107,"TopRuc":96,"TopOppRuc":92,"Top2Def":94,"Top2OppDef":95,"Top2For":101,"Top2OppFor":85},{"Team":"Brisbane Lions","Last":1662,"LastOpp":1638,"Season":1671,"SeasonOpp":1629,"Last3":1648,"Last3Opp":1653,"Top3Mid":113,"Top3OppMid":105,"TopRuc":94,"TopOppRuc":102,"Top2Def":96,"Top2OppDef":103,"Top2For":92,"Top2OppFor":82},{"Team":"Carlton","Last":1606,"LastOpp":1692,"Season":1708,"SeasonOpp":1592,"Last3":1679,"Last3Opp":1621,"Top3Mid":108,"Top3OppMid":102,"TopRuc":81,"TopOppRuc":90,"Top2Def":109,"Top2OppDef":102,"Top2For":96,"Top2OppFor":86},{"Team":"Collingwood","Last":1792,"LastOpp":1505,"Season":1710,"SeasonOpp":1591,"Last3":1728,"Last3Opp":1571,"Top3Mid":112,"Top3OppMid":105,"TopRuc":91,"TopOppRuc":90,"Top2Def":106,"Top2OppDef":100,"Top2For":85,"Top2OppFor":84},{"Team":"Essendon","Last":1505,"LastOpp":1792,"Season":1657,"SeasonOpp":1643,"Last3":1518,"Last3Opp":1780,"Top3Mid":109,"Top3OppMid":108,"TopRuc":72,"TopOppRuc":82,"Top2Def":107,"Top2OppDef":103,"Top2For":80,"Top2OppFor":92},{"Team":"Fremantle","Last":1747,"LastOpp":1554,"Season":1672,"SeasonOpp":1628,"Last3":1759,"Last3Opp":1542,"Top3Mid":108,"Top3OppMid":112,"TopRuc":113,"TopOppRuc":83,"Top2Def":106,"Top2OppDef":96,"Top2For":87,"Top2OppFor":85},{"Team":"GWS Giants","Last":1692,"LastOpp":1606,"Season":1675,"SeasonOpp":1626,"Last3":1737,"Last3Opp":1561,"Top3Mid":107,"Top3OppMid":104,"TopRuc":101,"TopOppRuc":101,"Top2Def":105,"Top2OppDef":103,"Top2For":94,"Top2OppFor":85},{"Team":"Geelong Cats","Last":1630,"LastOpp":1671,"Season":1642,"SeasonOpp":1657,"Last3":1527,"Last3Opp":1773,"Top3Mid":102,"Top3OppMid":107,"TopRuc":76,"TopOppRuc":91,"Top2Def":100,"Top2OppDef":101,"Top2For":97,"Top2OppFor":86},{"Team":"Gold Coast Suns","Last":1559,"LastOpp":1741,"Season":1603,"SeasonOpp":1696,"Last3":1557,"Last3Opp":1743,"Top3Mid":111,"Top3OppMid":109,"TopRuc":101,"TopOppRuc":79,"Top2Def":93,"Top2OppDef":106,"Top2For":86,"Top2OppFor":92},{"Team":"Hawthorn","Last":1554,"LastOpp":1747,"Season":1621,"SeasonOpp":1679,"Last3":1663,"Last3Opp":1636,"Top3Mid":105,"Top3OppMid":107,"TopRuc":80,"TopOppRuc":86,"Top2Def":106,"Top2OppDef":99,"Top2For":87,"Top2OppFor":92},{"Team":"Melbourne","Last":1657,"LastOpp":1643,"Season":1697,"SeasonOpp":1603,"Last3":1648,"Last3Opp":1651,"Top3Mid":114,"Top3OppMid":111,"TopRuc":111,"TopOppRuc":94,"Top2Def":98,"Top2OppDef":103,"Top2For":83,"Top2OppFor":79},{"Team":"North Melbourne","Last":1741,"LastOpp":1559,"Season":1553,"SeasonOpp":1747,"Last3":1608,"Last3Opp":1691,"Top3Mid":98,"Top3OppMid":114,"TopRuc":94,"TopOppRuc":87,"Top2Def":99,"Top2OppDef":101,"Top2For":88,"Top2OppFor":102},{"Team":"Port Adelaide","Last":1747,"LastOpp":1552,"Season":1657,"SeasonOpp":1643,"Last3":1725,"Last3Opp":1575,"Top3Mid":110,"Top3OppMid":107,"TopRuc":66,"TopOppRuc":113,"Top2Def":104,"Top2OppDef":102,"Top2For":92,"Top2OppFor":87},{"Team":"Richmond","Last":1552,"LastOpp":1747,"Season":1611,"SeasonOpp":1688,"Last3":1602,"Last3Opp":1696,"Top3Mid":103,"Top3OppMid":109,"TopRuc":100,"TopOppRuc":95,"Top2Def":104,"Top2OppDef":107,"Top2For":89,"Top2OppFor":92},{"Team":"St Kilda","Last":1638,"LastOpp":1662,"Season":1662,"SeasonOpp":1638,"Last3":1770,"Last3Opp":1529,"Top3Mid":100,"Top3OppMid":103,"TopRuc":114,"TopOppRuc":90,"Top2Def":105,"Top2OppDef":111,"Top2For":85,"Top2OppFor":88},{"Team":"Sydney Swans","Last":1643,"LastOpp":1657,"Season":1670,"SeasonOpp":1629,"Last3":1676,"Last3Opp":1622,"Top3Mid":109,"Top3OppMid":110,"TopRuc":73,"TopOppRuc":102,"Top2Def":103,"Top2OppDef":93,"Top2For":95,"Top2OppFor":89},{"Team":"West Coast Eagles","Last":1589,"LastOpp":1709,"Season":1505,"SeasonOpp":1795,"Last3":1556,"Last3Opp":1744,"Top3Mid":96,"Top3OppMid":118,"TopRuc":77,"TopOppRuc":104,"Top2Def":103,"Top2OppDef":105,"Top2For":82,"Top2OppFor":113},{"Team":"Western Bulldogs","Last":1671,"LastOpp":1630,"Season":1677,"SeasonOpp":1623,"Last3":1589,"Last3Opp":1711,"Top3Mid":121,"Top3OppMid":104,"TopRuc":128,"TopOppRuc":91,"Top2Def":97,"Top2OppDef":106,"Top2For":87,"Top2OppFor":85}]
